{
  "id": "a1fc271c-8095-4f5f-ac9f-f452f3334888",
  "workspaceRoot": "/Users/jim/src/apps/odd_manager",
  "label": "shell-17",
  "archived": true,
  "status": "closed",
  "shell": "/bin/zsh -f -i",
  "pid": 65125,
  "backend": "python-pty-service",
  "createdAt": "2026-04-28T17:56:53.174Z",
  "lastOutputAt": "2026-04-28T17:57:50.660Z",
  "attachedTrainId": null,
  "attachedStationId": null,
  "attachedEdgeId": null,
  "conversationHistoryId": "oddterm_a1fc271c-8095-4f5f-ac9f-f452f3334888",
  "historyBytes": 1156,
  "liveClientCount": 0,
  "exitCode": null,
  "signal": "SIGTERM"
}